{
  "users": [
    {
      "id": "u1a2",
      "name": "Luiza Cavalcante",
      "email": "luiza@example.com",
      "password": "password123"
    },
    {
      "id": "u3b4",
      "name": "João Silva",
      "email": "joao@example.com",
      "password": "password123"
    },
    {
      "id": "u5c6",
      "name": "Maria Oliveira",
      "email": "maria@example.com",
      "password": "password123"
    }
  ],
  "courses": [
    {
      "id": "c101",
      "name": "Introdução ao React",
      "description": "Curso introdutório sobre os fundamentos do React.",
      "start_date": "2025-08-01",
      "end_date": "2025-09-01",
      "creator_id": "u1a2",
      "instructors": ["u1a2", "u3b4"]
    },
    {
      "id": "c202",
      "name": "TypeScript Avançado",
      "description": "",
      "start_date": "2025-09-05",
      "end_date": "2025-10-05",
      "creator_id": "u3b4",
      "instructors": ["u3b4"]
    },
    {
      "id": "c303",
      "name": "Design Patterns em JavaScript",
      "description": "Aprenda os padrões mais usados no desenvolvimento frontend.",
      "start_date": "2025-10-10",
      "end_date": "2025-11-15",
      "creator_id": "u5c6",
      "instructors": ["u5c6", "u1a2"]
    },
    {
      "id": "c404",
      "name": "Testes Automatizados com Jest",
      "description": "Domine os testes unitários e de integração usando Jest.",
      "start_date": "2025-07-20",
      "end_date": "2025-08-20",
      "creator_id": "u1a2",
      "instructors": ["u1a2"]
    }
  ],
  "lessons": [
    {
      "id": "l001",
      "title": "JSX e Componentes",
      "status": "published",
      "publish_date": "2025-08-02",
      "video_url": "https://www.youtube.com/watch?v=dQw4w9WgXcQ",
      "creator_id": "u1a2",
      "course_id": "c101"
    },
    {
      "id": "l002",
      "title": "Hooks e Estado",
      "status": "draft",
      "publish_date": "2025-08-10",
      "video_url": "https://www.youtube.com/watch?v=dQw4w9WgXcQ",
      "creator_id": "u3b4",
      "course_id": "c101"
    },
    {
      "id": "l003",
      "title": "Configuração com tsconfig",
      "status": "published",
      "publish_date": "2025-09-06",
      "video_url": "https://www.youtube.com/watch?v=dQw4w9WgXcQ",
      "creator_id": "u3b4",
      "course_id": "c202"
    },
    {
      "id": "l004",
      "title": "Interfaces e Tipos",
      "status": "published",
      "publish_date": "2025-09-10",
      "video_url": "https://www.youtube.com/watch?v=dQw4w9WgXcQ",
      "creator_id": "u3b4",
      "course_id": "c202"
    },
    {
      "id": "l005",
      "title": "Observer Pattern",
      "status": "draft",
      "publish_date": "2025-10-15",
      "video_url": "https://www.youtube.com/watch?v=dQw4w9WgXcQ",
      "creator_id": "u5c6",
      "course_id": "c303"
    },
    {
      "id": "l006",
      "title": "Singleton Pattern",
      "status": "published",
      "publish_date": "2025-10-18",
      "video_url": "https://www.youtube.com/watch?v=dQw4w9WgXcQ",
      "creator_id": "u5c6",
      "course_id": "c303"
    },
    {
      "id": "l007",
      "title": "Testando Componentes React",
      "status": "published",
      "publish_date": "2025-07-21",
      "video_url": "https://www.youtube.com/watch?v=dQw4w9WgXcQ",
      "creator_id": "u1a2",
      "course_id": "c404"
    },
    {
      "id": "l008",
      "title": "Mocking com Jest",
      "status": "archived",
      "publish_date": "2025-07-25",
      "video_url": "https://www.youtube.com/watch?v=dQw4w9WgXcQ",
      "creator_id": "u1a2",
      "course_id": "c404"
    }
  ]
}
